evolut/__init__.py
evolut/core.py
evolut-1.4.dist-info/METADATA
evolut-1.4.dist-info/WHEEL
evolut-1.4.dist-info/top_level.txt
evolut-1.4.dist-info/RECORD
